{
   "results" : 
   [
      {
         "address_components" : 
         [
            {
               "long_name" : "Закарпатська область",
               "short_name" : "Закарпатська область",
               "types" : 
               [
                  "administrative_area_level_1",
                  "political"
               ]
            },
            {
               "long_name" : "Україна",
               "short_name" : "UA",
               "types" : 
               [
                  "country",
                  "political"
               ]
            }
         ],
         "formatted_address" : "Закарпатська область, Україна",
         "geometry" : 
         {
            "bounds" : 
            {
               "northeast" : 
               {
                  "lat" : 49.09732289999999,
                  "lng" : 24.627378
               },
               "southwest" : 
               {
                  "lat" : 47.896506,
                  "lng" : 22.1370556
               }
            },
            "location" : 
            {
               "lat" : 48.6208,
               "lng" : 22.287883
            },
            "location_type" : "APPROXIMATE",
            "viewport" : 
            {
               "northeast" : 
               {
                  "lat" : 49.09732289999999,
                  "lng" : 24.627378
               },
               "southwest" : 
               {
                  "lat" : 47.896506,
                  "lng" : 22.1370556
               }
            }
         },
         "place_id" : "ChIJDQKKqwsTOUcRLtC2-ZaZ5Fk",
         "types" : 
         [
            "administrative_area_level_1",
            "political"
         ]
      }
   ],
   "status" : "OK"
}