{
   "results" : 
   [
      {
         "address_components" : 
         [
            {
               "long_name" : "Чернігів",
               "short_name" : "Чернігів",
               "types" : 
               [
                  "locality",
                  "political"
               ]
            },
            {
               "long_name" : "Чернігівська міськрада",
               "short_name" : "Чернігівська міськрада",
               "types" : 
               [
                  "administrative_area_level_3",
                  "political"
               ]
            },
            {
               "long_name" : "Чернігівська область",
               "short_name" : "Чернігівська область",
               "types" : 
               [
                  "administrative_area_level_1",
                  "political"
               ]
            },
            {
               "long_name" : "Україна",
               "short_name" : "UA",
               "types" : 
               [
                  "country",
                  "political"
               ]
            },
            {
               "long_name" : "14000",
               "short_name" : "14000",
               "types" : 
               [
                  "postal_code"
               ]
            }
         ],
         "formatted_address" : "Чернігів, Чернігівська область, Україна, 14000",
         "geometry" : 
         {
            "bounds" : 
            {
               "northeast" : 
               {
                  "lat" : 51.557609,
                  "lng" : 31.3770221
               },
               "southwest" : 
               {
                  "lat" : 51.433951,
                  "lng" : 31.2040549
               }
            },
            "location" : 
            {
               "lat" : 51.4982,
               "lng" : 31.28935
            },
            "location_type" : "APPROXIMATE",
            "viewport" : 
            {
               "northeast" : 
               {
                  "lat" : 51.557609,
                  "lng" : 31.3770221
               },
               "southwest" : 
               {
                  "lat" : 48.3011017,
                  "lng" : 25.9303989
               }
            }
         },
         "partial_match" : true,
         "place_id" : "ChIJlzXucYlI1UYRtThg59NIIyo",
         "types" : 
         [
            "locality",
            "political"
         ]
      },
      {
         "address_components" : 
         [
            {
               "long_name" : "Чернігівський район",
               "short_name" : "Чернігівський район",
               "types" : 
               [
                  "administrative_area_level_2",
                  "political"
               ]
            },
            {
               "long_name" : "Чернігівська область",
               "short_name" : "Чернігівська область",
               "types" : 
               [
                  "administrative_area_level_1",
                  "political"
               ]
            },
            {
               "long_name" : "Україна",
               "short_name" : "UA",
               "types" : 
               [
                  "country",
                  "political"
               ]
            }
         ],
         "formatted_address" : "Чернігівський район, Чернігівська область, Україна",
         "geometry" : 
         {
            "bounds" : 
            {
               "northeast" : 
               {
                  "lat" : 51.7051801,
                  "lng" : 31.695354
               },
               "southwest" : 
               {
                  "lat" : 51.172694,
                  "lng" : 30.5400821
               }
            },
            "location" : 
            {
               "lat" : 51.3773101,
               "lng" : 30.9443955
            },
            "location_type" : "APPROXIMATE",
            "viewport" : 
            {
               "northeast" : 
               {
                  "lat" : 51.7051801,
                  "lng" : 31.695354
               },
               "southwest" : 
               {
                  "lat" : 51.172694,
                  "lng" : 30.5400821
               }
            }
         },
         "partial_match" : true,
         "place_id" : "ChIJ8eGKCCNF1UYRQPHQFM2rvLs",
         "types" : 
         [
            "administrative_area_level_2",
            "political"
         ]
      }
   ],
   "status" : "OK"
}